iterchain/__init__.py
iterchain/generators.py
iterchain/methods.py
iterchain-0.1.3.dist-info/LICENSE
iterchain-0.1.3.dist-info/METADATA
iterchain-0.1.3.dist-info/WHEEL
iterchain-0.1.3.dist-info/top_level.txt
iterchain-0.1.3.dist-info/RECORD
