Metadata-Version: 2.1
Name: iterchain
Version: 0.1.3
Summary: Simple and ergonomic iterator chaining for Python
Home-page: https://iterchain.readthedocs.io/en/stable/
Author: Evelyn-H
Author-email: hobert.evelyn@gmail.com
License: UNKNOWN
Download-URL: https://github.com/Evelyn-H/iterchain
Platform: UNKNOWN
Classifier: Programming Language :: Python :: 3
Classifier: Development Status :: 3 - Alpha
Classifier: License :: OSI Approved :: GNU General Public License v3 (GPLv3)
Classifier: Operating System :: OS Independent
